<annotation>
  <folder>val</folder>
  <filename>fish_94.jpg</filename>
  <path>/home/dgu/faster-rcnn.pytorch/data/train/fish_94.jpg</path>
  <size>
    <width>1245</width>
    <height>700</height>
    <depth>3</depth>
  </size>
  <object>
    <name>fish</name>
    <pose>Unspecified</pose>
    <truncated>0</truncated>
    <difficult>0</difficult>
    <bndbox>
      <xmin>517</xmin>
      <ymin>184</ymin>
      <xmax>868</xmax>
      <ymax>559</ymax>
    </bndbox>
  </object>
  <object>
    <name>fish</name>
    <pose>Unspecified</pose>
    <truncated>0</truncated>
    <difficult>0</difficult>
    <bndbox>
      <xmin>334</xmin>
      <ymin>331</ymin>
      <xmax>614</xmax>
      <ymax>546</ymax>
    </bndbox>
  </object>
</annotation>
